seqkan/__init__.py
seqkan/kan/KANLayer.py
seqkan/kan/LBFGS.py
seqkan/kan/MultKAN.py
seqkan/kan/Symbolic_KANLayer.py
seqkan/kan/__init__.py
seqkan/kan/assets/img/mult_symbol.png
seqkan/kan/assets/img/sum_symbol.png
seqkan/kan/hypothesis.py
seqkan/kan/spline.py
seqkan/kan/utils.py
seqkan/model.py
seqkan/train.py
seqkan/utils.py
testcases/__init__.py
testcases/bare_grid.py
testcases/one_layer.py
testcases/testcase_data.py
testcases/two_layers.py
seqkan-0.8.1.dist-info/LICENSE
seqkan-0.8.1.dist-info/METADATA
seqkan-0.8.1.dist-info/WHEEL
seqkan-0.8.1.dist-info/RECORD
